Workbook

Sheet Pivot_Analysis
A3: Row Labels | B3: Sum of Sales_Value
A4: Electronics | B4: 985800
A5: Furniture | B5: 321000
A6: Grand Total | B6: 1306800

Sheet Sales_Data
A1: Sale_ID | B1: Sale_Date | C1: Customer_Name | D1: City | E1: Product_ID | F1: Product_Name | G1: Category | H1: Quantity | I1: Unit_Price | J1: Payment_Mode | K1: Salesperson | L1: Sales_Value | M1: Sales_Level | N1: Metric | O1: Result | P1: VLOOKUP_Result | Q1: XLOOKUP_Result
A2: 1001 | B2: 46266 | C2: Rahul Sharma | D2: Delhi | E2: 101 | F2: Laptop | G2: Electronics | H2: 1 | I2: 60000 | J2: UPI | K2: Ankit | L2: =H2*I2 -> 60000 | M2: =IF(L2>=50000,"High","Normal") -> High | N2: High Value Sales Count | O2: =COUNTIF(M2:M31,"High") -> 7 | P2: =VLOOKUP(E2,Product_Lookup!$A$2:$D$9,2,FALSE) -> Laptop | Q2: =_xlfn.XLOOKUP(E2,Product_Lookup!$A$2:$A$9,Product_Lookup!$B$2:$B$9) -> Laptop
A3: 1009 | B3: 46274 | C3: Rahul Sharma | D3: Delhi | E3: 101 | F3: Laptop | G3: Electronics | H3: 4 | I3: 60000 | J3: UPI | K3: Neha | L3: =H3*I3 -> 240000 | M3: =IF(L3>=50000,"High","Normal") -> High | N3: Electronics Sales Value | O3: =SUMIF(G2:G31,"Electronics",L2:L31) -> 985800 | P3: =VLOOKUP(E3,Product_Lookup!$A$2:$D$9,2,FALSE) -> Laptop | Q3: =_xlfn.XLOOKUP(E3,Product_Lookup!$A$2:$A$9,Product_Lookup!$B$2:$B$9) -> Laptop
A4: 1017 | B4: 46267 | C4: Rahul Sharma | D4: Delhi | E4: 101 | F4: Laptop | G4: Electronics | H4: 2 | I4: 60000 | J4: UPI | K4: Priya | L4: =H4*I4 -> 120000 | M4: =IF(L4>=50000,"High","Normal") -> High | P4: =VLOOKUP(E4,Product_Lookup!$A$2:$D$9,2,FALSE) -> Laptop | Q4: =_xlfn.XLOOKUP(E4,Product_Lookup!$A$2:$A$9,Product_Lookup!$B$2:$B$9) -> Laptop
A5: 1025 | B5: 46275 | C5: Rahul Sharma | D5: Delhi | E5: 101 | F5: Laptop | G5: Electronics | H5: 5 | I5: 60000 | J5: UPI | K5: Vikram | L5: =H5*I5 -> 300000 | M5: =IF(L5>=50000,"High","Normal") -> High | P5: =VLOOKUP(E5,Product_Lookup!$A$2:$D$9,2,FALSE) -> Laptop | Q5: =_xlfn.XLOOKUP(E5,Product_Lookup!$A$2:$A$9,Product_Lookup!$B$2:$B$9) -> Laptop
A6: 1006 | B6: 46271 | C6: Karan Malhotra | D6: Jaipur | E6: 106 | F6: Monitor | G6: Electronics | H6: 1 | I6: 18000 | J6: Credit Card | K6: Ankit | L6: =H6*I6 -> 18000 | M6: =IF(L6>=50000,"High","Normal") -> Normal | P6: =VLOOKUP(E6,Product_Lookup!$A$2:$D$9,2,FALSE) -> Monitor | Q6: =_xlfn.XLOOKUP(E6,Product_Lookup!$A$2:$A$9,Product_Lookup!$B$2:$B$9) -> Monitor
A7: 1014 | B7: 46279 | C7: Karan Malhotra | D7: Jaipur | E7: 106 | F7: Monitor | G7: Electronics | H7: 4 | I7: 18000 | J7: Credit Card | K7: Neha | L7: =H7*I7 -> 72000 | M7: =IF(L7>=50000,"High","Normal") -> High | P7: =VLOOKUP(E7,Product_Lookup!$A$2:$D$9,2,FALSE) -> Monitor | Q7: =_xlfn.XLOOKUP(E7,Product_Lookup!$A$2:$A$9,Product_Lookup!$B$2:$B$9) -> Monitor
A8: 1022 | B8: 46272 | C8: Karan Malhotra | D8: Jaipur | E8: 106 | F8: Monitor | G8: Electronics | H8: 2 | I8: 18000 | J8: Credit Card | K8: Priya | L8: =H8*I8 -> 36000 | M8: =IF(L8>=50000,"High","Normal") -> Normal | P8: =VLOOKUP(E8,Product_Lookup!$A$2:$D$9,2,FALSE) -> Monitor | Q8: =_xlfn.XLOOKUP(E8,Product_Lookup!$A$2:$A$9,Product_Lookup!$B$2:$B$9) -> Monitor
A9: 1030 | B9: 46280 | C9: Karan Malhotra | D9: Jaipur | E9: 106 | F9: Monitor | G9: Electronics | H9: 5 | I9: 18000 | J9: Credit Card | K9: Vikram | L9: =H9*I9 -> 90000 | M9: =IF(L9>=50000,"High","Normal") -> High | P9: =VLOOKUP(E9,Product_Lookup!$A$2:$D$9,2,FALSE) -> Monitor | Q9: =_xlfn.XLOOKUP(E9,Product_Lookup!$A$2:$A$9,Product_Lookup!$B$2:$B$9) -> Monitor
A10: 1005 | B10: 46270 | C10: Rohan Verma | D10: Delhi | E10: 105 | F10: Desk | G10: Furniture | H10: 5 | I10: 12000 | J10: UPI | K10: Vikram | L10: =H10*I10 -> 60000 | M10: =IF(L10>=50000,"High","Normal") -> High | P10: =VLOOKUP(E10,Product_Lookup!$A$2:$D$9,2,FALSE) -> Desk | Q10: =_xlfn.XLOOKUP(E10,Product_Lookup!$A$2:$A$9,Product_Lookup!$B$2:$B$9) -> Desk
A11: 1013 | B11: 46278 | C11: Rohan Verma | D11: Delhi | E11: 105 | F11: Desk | G11: Furniture | H11: 3 | I11: 12000 | J11: UPI | K11: Rahul | L11: =H11*I11 -> 36000 | M11: =IF(L11>=50000,"High","Normal") -> Normal | P11: =VLOOKUP(E11,Product_Lookup!$A$2:$D$9,2,FALSE) -> Desk | Q11: =_xlfn.XLOOKUP(E11,Product_Lookup!$A$2:$A$9,Product_Lookup!$B$2:$B$9) -> Desk
A12: 1021 | B12: 46271 | C12: Rohan Verma | D12: Delhi | E12: 105 | F12: Desk | G12: Furniture | H12: 1 | I12: 12000 | J12: UPI | K12: Ankit | L12: =H12*I12 -> 12000 | M12: =IF(L12>=50000,"High","Normal") -> Normal | P12: =VLOOKUP(E12,Product_Lookup!$A$2:$D$9,2,FALSE) -> Desk | Q12: =_xlfn.XLOOKUP(E12,Product_Lookup!$A$2:$A$9,Product_Lookup!$B$2:$B$9) -> Desk
A13: 1029 | B13: 46279 | C13: Rohan Verma | D13: Delhi | E13: 105 | F13: Desk | G13: Furniture | H13: 4 | I13: 12000 | J13: UPI | K13: Neha | L13: =H13*I13 -> 48000 | M13: =IF(L13>=50000,"High","Normal") -> Normal | P13: =VLOOKUP(E13,Product_Lookup!$A$2:$D$9,2,FALSE) -> Desk | Q13: =_xlfn.XLOOKUP(E13,Product_Lookup!$A$2:$A$9,Product_Lookup!$B$2:$B$9) -> Desk
A14: 1007 | B14: 46272 | C14: Simran Kaur | D14: Chandigarh | E14: 107 | F14: Bookshelf | G14: Furniture | H14: 2 | I14: 9000 | J14: Debit Card | K14: Priya | L14: =H14*I14 -> 18000 | M14: =IF(L14>=50000,"High","Normal") -> Normal | P14: =VLOOKUP(E14,Product_Lookup!$A$2:$D$9,2,FALSE) -> Bookshelf | Q14: =_xlfn.XLOOKUP(E14,Product_Lookup!$A$2:$A$9,Product_Lookup!$B$2:$B$9) -> Bookshelf
A15: 1015 | B15: 46280 | C15: Simran Kaur | D15: Chandigarh | E15: 107 | F15: Bookshelf | G15: Furniture | H15: 5 | I15: 9000 | J15: Debit Card | K15: Vikram | L15: =H15*I15 -> 45000 | M15: =IF(L15>=50000,"High","Normal") -> Normal | P15: =VLOOKUP(E15,Product_Lookup!$A$2:$D$9,2,FALSE) -> Bookshelf | Q15: =_xlfn.XLOOKUP(E15,Product_Lookup!$A$2:$A$9,Product_Lookup!$B$2:$B$9) -> Bookshelf
... A31: 1026 | B31: 46276 | C31: Priya Mehta | D31: Mumbai | E31: 102 | F31: Mouse | G31: Electronics | H31: 1 | I31: 800 | J31: Credit Card | K31: Ankit | L31: =H31*I31 -> 800 | M31: =IF(L31>=50000,"High","Normal") -> Normal | P31: =VLOOKUP(E31,Product_Lookup!$A$2:$D$9,2,FALSE) -> Mouse | Q31: =_xlfn.XLOOKUP(E31,Product_Lookup!$A$2:$A$9,Product_Lookup!$B$2:$B$9) -> Mouse

Sheet Product_Lookup
A1: Product_ID | B1: Product_Name | C1: Category | D1: Unit_Price
A2: 101 | B2: Laptop | C2: Electronics | D2: 60000
A3: 102 | B3: Mouse | C3: Electronics | D3: 800
A4: 103 | B4: Office Chair | C4: Furniture | D4: 7500
A5: 104 | B5: Keyboard | C5: Electronics | D5: 1500
A6: 105 | B6: Desk | C6: Furniture | D6: 12000
A7: 106 | B7: Monitor | C7: Electronics | D7: 18000
A8: 107 | B8: Bookshelf | C8: Furniture | D8: 9000
A9: 108 | B9: Headphones | C9: Electronics | D9: 2500
